[
    {
        "game_platform_id": "6112",
        "game_name": "_json:{\"1\":\"12D\",\"2\":\"12D\",\"3\":\"12D\",\"4\":\"12D\",\"5\":\"12D\"}",
        "game_code": "12d",
        "progressive": false,
        "dlc_enabled": 0,
        "flash_enabled": 0,
        "offline_enabled": 0,
        "mobile_enabled": true,
        "note": null,
        "status": true,
        "flag_show_in_site": true,
        "no_cash_back": false,
        "void_bet": false,
        "attributes": null,
        "game_order": null,
        "html_five_enabled": true,
        "english_name": "12D",
        "external_game_id": "12d",
        "clientid": null,
        "moduleid": null,
        "related_game_desc_id": null,
        "enabled_freespin": 0,
        "sub_game_provider": null,
        "enabled_on_android": true,
        "enabled_on_ios": true,
        "flag_new_game": true,
        "game_type_code": "live_dealer"
    },
    {
        "game_platform_id": "6112",
        "game_name": "_json:{\"1\":\"24D\",\"2\":\"24D\",\"3\":\"24D\",\"4\":\"24D\",\"5\":\"24D\"}",
        "game_code": "24d",
        "progressive": false,
        "dlc_enabled": 0,
        "flash_enabled": 0,
        "offline_enabled": 0,
        "mobile_enabled": true,
        "note": null,
        "status": true,
        "flag_show_in_site": true,
        "no_cash_back": false,
        "void_bet": false,
        "attributes": null,
        "game_order": null,
        "html_five_enabled": true,
        "english_name": "24D",
        "external_game_id": "24d",
        "clientid": null,
        "moduleid": null,
        "related_game_desc_id": null,
        "enabled_freespin": 0,
        "sub_game_provider": null,
        "enabled_on_android": true,
        "enabled_on_ios": true,
        "flag_new_game": true,
        "game_type_code": "live_dealer"
    },
    {
        "game_platform_id": "6112",
        "game_name": "_json:{\"1\":\"24Dspin\",\"2\":\"24Dspin\",\"3\":\"24Dspin\",\"4\":\"24Dspin\",\"5\":\"24Dspin\"}",
        "game_code": "24dspin",
        "progressive": false,
        "dlc_enabled": 0,
        "flash_enabled": 0,
        "offline_enabled": 0,
        "mobile_enabled": true,
        "note": null,
        "status": true,
        "flag_show_in_site": true,
        "no_cash_back": false,
        "void_bet": false,
        "attributes": null,
        "game_order": null,
        "html_five_enabled": true,
        "english_name": "24Dspin",
        "external_game_id": "24dspin",
        "clientid": null,
        "moduleid": null,
        "related_game_desc_id": null,
        "enabled_freespin": 0,
        "sub_game_provider": null,
        "enabled_on_android": true,
        "enabled_on_ios": true,
        "flag_new_game": true,
        "game_type_code": "live_dealer"
    },
    {
        "game_platform_id": "6112",
        "game_name": "_json:{\"1\":\"3D Shio\",\"2\":\"3D Shio\",\"3\":\"3D Shio\",\"4\":\"3D Shio\",\"5\":\"3D Shio\"}",
        "game_code": "shioballs",
        "progressive": false,
        "dlc_enabled": 0,
        "flash_enabled": 0,
        "offline_enabled": 0,
        "mobile_enabled": true,
        "note": null,
        "status": true,
        "flag_show_in_site": true,
        "no_cash_back": false,
        "void_bet": false,
        "attributes": null,
        "game_order": null,
        "html_five_enabled": true,
        "english_name": "3D Shio",
        "external_game_id": "shioballs",
        "clientid": null,
        "moduleid": null,
        "related_game_desc_id": null,
        "enabled_freespin": 0,
        "sub_game_provider": null,
        "enabled_on_android": true,
        "enabled_on_ios": true,
        "flag_new_game": true,
        "game_type_code": "live_dealer"
    },
    {
        "game_platform_id": "6112",
        "game_name": "_json:{\"1\":\"48D\",\"2\":\"48D\",\"3\":\"48D\",\"4\":\"48D\",\"5\":\"48D\"}",
        "game_code": "48d",
        "progressive": false,
        "dlc_enabled": 0,
        "flash_enabled": 0,
        "offline_enabled": 0,
        "mobile_enabled": true,
        "note": null,
        "status": true,
        "flag_show_in_site": true,
        "no_cash_back": false,
        "void_bet": false,
        "attributes": null,
        "game_order": null,
        "html_five_enabled": true,
        "english_name": "48D",
        "external_game_id": "48d",
        "clientid": null,
        "moduleid": null,
        "related_game_desc_id": null,
        "enabled_freespin": 0,
        "sub_game_provider": null,
        "enabled_on_android": true,
        "enabled_on_ios": true,
        "flag_new_game": true,
        "game_type_code": "live_dealer"
    },
    {
        "game_platform_id": "6112",
        "game_name": "_json:{\"1\":\"5D\",\"2\":\"5D\",\"3\":\"5D\",\"4\":\"5D\",\"5\":\"5D\"}",
        "game_code": "5d",
        "progressive": false,
        "dlc_enabled": 0,
        "flash_enabled": 0,
        "offline_enabled": 0,
        "mobile_enabled": true,
        "note": null,
        "status": true,
        "flag_show_in_site": true,
        "no_cash_back": false,
        "void_bet": false,
        "attributes": null,
        "game_order": null,
        "html_five_enabled": true,
        "english_name": "5D",
        "external_game_id": "5d",
        "clientid": null,
        "moduleid": null,
        "related_game_desc_id": null,
        "enabled_freespin": 0,
        "sub_game_provider": null,
        "enabled_on_android": true,
        "enabled_on_ios": true,
        "flag_new_game": true,
        "game_type_code": "live_dealer"
    },
    {
        "game_platform_id": "6112",
        "game_name": "_json:{\"1\":\"Baccarat\",\"2\":\"Baccarat\",\"3\":\"Baccarat\",\"4\":\"Baccarat\",\"5\":\"Baccarat\"}",
        "game_code": "baccarat",
        "progressive": false,
        "dlc_enabled": 0,
        "flash_enabled": 0,
        "offline_enabled": 0,
        "mobile_enabled": true,
        "note": null,
        "status": true,
        "flag_show_in_site": true,
        "no_cash_back": false,
        "void_bet": false,
        "attributes": null,
        "game_order": null,
        "html_five_enabled": true,
        "english_name": "Baccarat",
        "external_game_id": "baccarat",
        "clientid": null,
        "moduleid": null,
        "related_game_desc_id": null,
        "enabled_freespin": 0,
        "sub_game_provider": null,
        "enabled_on_android": true,
        "enabled_on_ios": true,
        "flag_new_game": true,
        "game_type_code": "live_dealer"
    },
    {
        "game_platform_id": "6112",
        "game_name": "_json:{\"1\":\"Baccarat B\",\"2\":\"Baccarat B\",\"3\":\"Baccarat B\",\"4\":\"Baccarat B\",\"5\":\"Baccarat B\"}",
        "game_code": "baccaratb",
        "progressive": false,
        "dlc_enabled": 0,
        "flash_enabled": 0,
        "offline_enabled": 0,
        "mobile_enabled": true,
        "note": null,
        "status": true,
        "flag_show_in_site": true,
        "no_cash_back": false,
        "void_bet": false,
        "attributes": null,
        "game_order": null,
        "html_five_enabled": true,
        "english_name": "Baccarat B",
        "external_game_id": "baccaratb",
        "clientid": null,
        "moduleid": null,
        "related_game_desc_id": null,
        "enabled_freespin": 0,
        "sub_game_provider": null,
        "enabled_on_android": true,
        "enabled_on_ios": true,
        "flag_new_game": true,
        "game_type_code": "live_dealer"
    },
    {
        "game_platform_id": "6112",
        "game_name": "_json:{\"1\":\"Baccarat C\",\"2\":\"Baccarat C\",\"3\":\"Baccarat C\",\"4\":\"Baccarat C\",\"5\":\"Baccarat C\"}",
        "game_code": "baccaratc",
        "progressive": false,
        "dlc_enabled": 0,
        "flash_enabled": 0,
        "offline_enabled": 0,
        "mobile_enabled": true,
        "note": null,
        "status": true,
        "flag_show_in_site": true,
        "no_cash_back": false,
        "void_bet": false,
        "attributes": null,
        "game_order": null,
        "html_five_enabled": true,
        "english_name": "Baccarat C",
        "external_game_id": "baccaratc",
        "clientid": null,
        "moduleid": null,
        "related_game_desc_id": null,
        "enabled_freespin": 0,
        "sub_game_provider": null,
        "enabled_on_android": true,
        "enabled_on_ios": true,
        "flag_new_game": true,
        "game_type_code": "live_dealer"
    },
    {
        "game_platform_id": "6112",
        "game_name": "_json:{\"1\":\"Baccarat D\",\"2\":\"Baccarat D\",\"3\":\"Baccarat D\",\"4\":\"Baccarat D\",\"5\":\"Baccarat D\"}",
        "game_code": "baccaratd",
        "progressive": false,
        "dlc_enabled": 0,
        "flash_enabled": 0,
        "offline_enabled": 0,
        "mobile_enabled": true,
        "note": null,
        "status": true,
        "flag_show_in_site": true,
        "no_cash_back": false,
        "void_bet": false,
        "attributes": null,
        "game_order": null,
        "html_five_enabled": true,
        "english_name": "Baccarat D",
        "external_game_id": "baccaratd",
        "clientid": null,
        "moduleid": null,
        "related_game_desc_id": null,
        "enabled_freespin": 0,
        "sub_game_provider": null,
        "enabled_on_android": true,
        "enabled_on_ios": true,
        "flag_new_game": true,
        "game_type_code": "live_dealer"
    },
    {
        "game_platform_id": "6112",
        "game_name": "_json:{\"1\":\"Baccarat Lobby\",\"2\":\"Baccarat Lobby\",\"3\":\"Baccarat Lobby\",\"4\":\"Baccarat Lobby\",\"5\":\"Baccarat Lobby\"}",
        "game_code": "baccarat-lobby",
        "progressive": false,
        "dlc_enabled": 0,
        "flash_enabled": 0,
        "offline_enabled": 0,
        "mobile_enabled": true,
        "note": null,
        "status": true,
        "flag_show_in_site": true,
        "no_cash_back": false,
        "void_bet": false,
        "attributes": null,
        "game_order": null,
        "html_five_enabled": true,
        "english_name": "Baccarat Lobby",
        "external_game_id": "baccarat-lobby",
        "clientid": null,
        "moduleid": null,
        "related_game_desc_id": null,
        "enabled_freespin": 0,
        "sub_game_provider": null,
        "enabled_on_android": true,
        "enabled_on_ios": true,
        "flag_new_game": true,
        "game_type_code": "live_dealer"
    },
    {
        "game_platform_id": "6112",
        "game_name": "_json:{\"1\":\"Billiards\",\"2\":\"Billiards\",\"3\":\"Billiards\",\"4\":\"Billiards\",\"5\":\"Billiards\"}",
        "game_code": "billiards",
        "progressive": false,
        "dlc_enabled": 0,
        "flash_enabled": 0,
        "offline_enabled": 0,
        "mobile_enabled": true,
        "note": null,
        "status": true,
        "flag_show_in_site": true,
        "no_cash_back": false,
        "void_bet": false,
        "attributes": null,
        "game_order": null,
        "html_five_enabled": true,
        "english_name": "Billiards",
        "external_game_id": "billiards",
        "clientid": null,
        "moduleid": null,
        "related_game_desc_id": null,
        "enabled_freespin": 0,
        "sub_game_provider": null,
        "enabled_on_android": true,
        "enabled_on_ios": true,
        "flag_new_game": true,
        "game_type_code": "live_dealer"
    },
    {
        "game_platform_id": "6112",
        "game_name": "_json:{\"1\":\"Bingo Sicbo\",\"2\":\"Bingo Sicbo\",\"3\":\"Bingo Sicbo\",\"4\":\"Bingo Sicbo\",\"5\":\"Bingo Sicbo\"}",
        "game_code": "bingosicbo",
        "progressive": false,
        "dlc_enabled": 0,
        "flash_enabled": 0,
        "offline_enabled": 0,
        "mobile_enabled": true,
        "note": null,
        "status": true,
        "flag_show_in_site": true,
        "no_cash_back": false,
        "void_bet": false,
        "attributes": null,
        "game_order": null,
        "html_five_enabled": true,
        "english_name": "Bingo Sicbo",
        "external_game_id": "bingosicbo",
        "clientid": null,
        "moduleid": null,
        "related_game_desc_id": null,
        "enabled_freespin": 0,
        "sub_game_provider": null,
        "enabled_on_android": true,
        "enabled_on_ios": true,
        "flag_new_game": true,
        "game_type_code": "live_dealer"
    },
    {
        "game_platform_id": "6112",
        "game_name": "_json:{\"1\":\"Dice 6\",\"2\":\"Dice 6\",\"3\":\"Dice 6\",\"4\":\"Dice 6\",\"5\":\"Dice 6\"}",
        "game_code": "dice6",
        "progressive": false,
        "dlc_enabled": 0,
        "flash_enabled": 0,
        "offline_enabled": 0,
        "mobile_enabled": true,
        "note": null,
        "status": true,
        "flag_show_in_site": true,
        "no_cash_back": false,
        "void_bet": false,
        "attributes": null,
        "game_order": null,
        "html_five_enabled": true,
        "english_name": "Dice 6",
        "external_game_id": "dice6",
        "clientid": null,
        "moduleid": null,
        "related_game_desc_id": null,
        "enabled_freespin": 0,
        "sub_game_provider": null,
        "enabled_on_android": true,
        "enabled_on_ios": true,
        "flag_new_game": true,
        "game_type_code": "live_dealer"
    },
    {
        "game_platform_id": "6112",
        "game_name": "_json:{\"1\":\"Dragon Tiger\",\"2\":\"Dragon Tiger\",\"3\":\"Dragon Tiger\",\"4\":\"Dragon Tiger\",\"5\":\"Dragon Tiger\"}",
        "game_code": "dragontiger",
        "progressive": false,
        "dlc_enabled": 0,
        "flash_enabled": 0,
        "offline_enabled": 0,
        "mobile_enabled": true,
        "note": null,
        "status": true,
        "flag_show_in_site": true,
        "no_cash_back": false,
        "void_bet": false,
        "attributes": null,
        "game_order": null,
        "html_five_enabled": true,
        "english_name": "Dragon Tiger",
        "external_game_id": "dragontiger",
        "clientid": null,
        "moduleid": null,
        "related_game_desc_id": null,
        "enabled_freespin": 0,
        "sub_game_provider": null,
        "enabled_on_android": true,
        "enabled_on_ios": true,
        "flag_new_game": true,
        "game_type_code": "live_dealer"
    },
    {
        "game_platform_id": "6112",
        "game_name": "_json:{\"1\":\"Fantan\",\"2\":\"Fantan\",\"3\":\"Fantan\",\"4\":\"Fantan\",\"5\":\"Fantan\"}",
        "game_code": "fantan",
        "progressive": false,
        "dlc_enabled": 0,
        "flash_enabled": 0,
        "offline_enabled": 0,
        "mobile_enabled": true,
        "note": null,
        "status": true,
        "flag_show_in_site": true,
        "no_cash_back": false,
        "void_bet": false,
        "attributes": null,
        "game_order": null,
        "html_five_enabled": true,
        "english_name": "Fantan",
        "external_game_id": "fantan",
        "clientid": null,
        "moduleid": null,
        "related_game_desc_id": null,
        "enabled_freespin": 0,
        "sub_game_provider": null,
        "enabled_on_android": true,
        "enabled_on_ios": true,
        "flag_new_game": true,
        "game_type_code": "live_dealer"
    },
    {
        "game_platform_id": "6112",
        "game_name": "_json:{\"1\":\"Gong Ball\",\"2\":\"Gong Ball\",\"3\":\"Gong Ball\",\"4\":\"Gong Ball\",\"5\":\"Gong Ball\"}",
        "game_code": "gongball",
        "progressive": false,
        "dlc_enabled": 0,
        "flash_enabled": 0,
        "offline_enabled": 0,
        "mobile_enabled": true,
        "note": null,
        "status": true,
        "flag_show_in_site": true,
        "no_cash_back": false,
        "void_bet": false,
        "attributes": null,
        "game_order": null,
        "html_five_enabled": true,
        "english_name": "Gong Ball",
        "external_game_id": "gongball",
        "clientid": null,
        "moduleid": null,
        "related_game_desc_id": null,
        "enabled_freespin": 0,
        "sub_game_provider": null,
        "enabled_on_android": true,
        "enabled_on_ios": true,
        "flag_new_game": true,
        "game_type_code": "live_dealer"
    },
    {
        "game_platform_id": "6112",
        "game_name": "_json:{\"1\":\"Gongball Jitu\",\"2\":\"Gongball Jitu\",\"3\":\"Gongball Jitu\",\"4\":\"Gongball Jitu\",\"5\":\"Gongball Jitu\"}",
        "game_code": "gongballjitu",
        "progressive": false,
        "dlc_enabled": 0,
        "flash_enabled": 0,
        "offline_enabled": 0,
        "mobile_enabled": true,
        "note": null,
        "status": true,
        "flag_show_in_site": true,
        "no_cash_back": false,
        "void_bet": false,
        "attributes": null,
        "game_order": null,
        "html_five_enabled": true,
        "english_name": "Gongball Jitu",
        "external_game_id": "gongballjitu",
        "clientid": null,
        "moduleid": null,
        "related_game_desc_id": null,
        "enabled_freespin": 0,
        "sub_game_provider": null,
        "enabled_on_android": true,
        "enabled_on_ios": true,
        "flag_new_game": true,
        "game_type_code": "live_dealer"
    },
    {
        "game_platform_id": "6112",
        "game_name": "_json:{\"1\":\"Grandprix\",\"2\":\"Grandprix\",\"3\":\"Grandprix\",\"4\":\"Grandprix\",\"5\":\"Grandprix\"}",
        "game_code": "grandprix",
        "progressive": false,
        "dlc_enabled": 0,
        "flash_enabled": 0,
        "offline_enabled": 0,
        "mobile_enabled": true,
        "note": null,
        "status": true,
        "flag_show_in_site": true,
        "no_cash_back": false,
        "void_bet": false,
        "attributes": null,
        "game_order": null,
        "html_five_enabled": true,
        "english_name": "Grandprix",
        "external_game_id": "grandprix",
        "clientid": null,
        "moduleid": null,
        "related_game_desc_id": null,
        "enabled_freespin": 0,
        "sub_game_provider": null,
        "enabled_on_android": true,
        "enabled_on_ios": true,
        "flag_new_game": true,
        "game_type_code": "live_dealer"
    },
    {
        "game_platform_id": "6112",
        "game_name": "_json:{\"1\":\"Head Tail\",\"2\":\"Head Tail\",\"3\":\"Head Tail\",\"4\":\"Head Tail\",\"5\":\"Head Tail\"}",
        "game_code": "headtail",
        "progressive": false,
        "dlc_enabled": 0,
        "flash_enabled": 0,
        "offline_enabled": 0,
        "mobile_enabled": true,
        "note": null,
        "status": true,
        "flag_show_in_site": true,
        "no_cash_back": false,
        "void_bet": false,
        "attributes": null,
        "game_order": null,
        "html_five_enabled": true,
        "english_name": "Head Tail",
        "external_game_id": "headtail",
        "clientid": null,
        "moduleid": null,
        "related_game_desc_id": null,
        "enabled_freespin": 0,
        "sub_game_provider": null,
        "enabled_on_android": true,
        "enabled_on_ios": true,
        "flag_new_game": true,
        "game_type_code": "live_dealer"
    },
    {
        "game_platform_id": "6112",
        "game_name": "_json:{\"1\":\"IDN 4 Stand\",\"2\":\"IDN 4 Stand\",\"3\":\"IDN 4 Stand\",\"4\":\"IDN 4 Stand\",\"5\":\"IDN 4 Stand\"}",
        "game_code": "idn4stand",
        "progressive": false,
        "dlc_enabled": 0,
        "flash_enabled": 0,
        "offline_enabled": 0,
        "mobile_enabled": true,
        "note": null,
        "status": true,
        "flag_show_in_site": true,
        "no_cash_back": false,
        "void_bet": false,
        "attributes": null,
        "game_order": null,
        "html_five_enabled": true,
        "english_name": "IDN 4 Stand",
        "external_game_id": "idn4stand",
        "clientid": null,
        "moduleid": null,
        "related_game_desc_id": null,
        "enabled_freespin": 0,
        "sub_game_provider": null,
        "enabled_on_android": true,
        "enabled_on_ios": true,
        "flag_new_game": true,
        "game_type_code": "live_dealer"
    },
    {
        "game_platform_id": "6112",
        "game_name": "_json:{\"1\":\"IDN 4 Stand B\",\"2\":\"IDN 4 Stand B\",\"3\":\"IDN 4 Stand B\",\"4\":\"IDN 4 Stand B\",\"5\":\"IDN 4 Stand B\"}",
        "game_code": "idn4standb",
        "progressive": false,
        "dlc_enabled": 0,
        "flash_enabled": 0,
        "offline_enabled": 0,
        "mobile_enabled": true,
        "note": null,
        "status": true,
        "flag_show_in_site": true,
        "no_cash_back": false,
        "void_bet": false,
        "attributes": null,
        "game_order": null,
        "html_five_enabled": true,
        "english_name": "IDN 4 Stand B",
        "external_game_id": "idn4standb",
        "clientid": null,
        "moduleid": null,
        "related_game_desc_id": null,
        "enabled_freespin": 0,
        "sub_game_provider": null,
        "enabled_on_android": true,
        "enabled_on_ios": true,
        "flag_new_game": true,
        "game_type_code": "live_dealer"
    },
    {
        "game_platform_id": "6112",
        "game_name": "_json:{\"1\":\"Lottery 8 Balls\",\"2\":\"Lottery 8 Balls\",\"3\":\"Lottery 8 Balls\",\"4\":\"Lottery 8 Balls\",\"5\":\"Lottery 8 Balls\"}",
        "game_code": "lottery8balls",
        "progressive": false,
        "dlc_enabled": 0,
        "flash_enabled": 0,
        "offline_enabled": 0,
        "mobile_enabled": true,
        "note": null,
        "status": true,
        "flag_show_in_site": true,
        "no_cash_back": false,
        "void_bet": false,
        "attributes": null,
        "game_order": null,
        "html_five_enabled": true,
        "english_name": "Lottery 8 Balls",
        "external_game_id": "lottery8balls",
        "clientid": null,
        "moduleid": null,
        "related_game_desc_id": null,
        "enabled_freespin": 0,
        "sub_game_provider": null,
        "enabled_on_android": true,
        "enabled_on_ios": true,
        "flag_new_game": true,
        "game_type_code": "live_dealer"
    },
    {
        "game_platform_id": "6112",
        "game_name": "_json:{\"1\":\"Lotto (Race Ball)\",\"2\":\"Lotto (Race Ball)\",\"3\":\"Lotto (Race Ball)\",\"4\":\"Lotto (Race Ball)\",\"5\":\"Lotto (Race Ball)\"}",
        "game_code": "lotto",
        "progressive": false,
        "dlc_enabled": 0,
        "flash_enabled": 0,
        "offline_enabled": 0,
        "mobile_enabled": true,
        "note": null,
        "status": true,
        "flag_show_in_site": true,
        "no_cash_back": false,
        "void_bet": false,
        "attributes": null,
        "game_order": null,
        "html_five_enabled": true,
        "english_name": "Lotto (Race Ball)",
        "external_game_id": "lotto",
        "clientid": null,
        "moduleid": null,
        "related_game_desc_id": null,
        "enabled_freespin": 0,
        "sub_game_provider": null,
        "enabled_on_android": true,
        "enabled_on_ios": true,
        "flag_new_game": true,
        "game_type_code": "live_dealer"
    },
    {
        "game_platform_id": "6112",
        "game_name": "_json:{\"1\":\"Monopoly\",\"2\":\"Monopoly\",\"3\":\"Monopoly\",\"4\":\"Monopoly\",\"5\":\"Monopoly\"}",
        "game_code": "mp",
        "progressive": false,
        "dlc_enabled": 0,
        "flash_enabled": 0,
        "offline_enabled": 0,
        "mobile_enabled": true,
        "note": null,
        "status": true,
        "flag_show_in_site": true,
        "no_cash_back": false,
        "void_bet": false,
        "attributes": null,
        "game_order": null,
        "html_five_enabled": true,
        "english_name": "Monopoly",
        "external_game_id": "mp",
        "clientid": null,
        "moduleid": null,
        "related_game_desc_id": null,
        "enabled_freespin": 0,
        "sub_game_provider": null,
        "enabled_on_android": true,
        "enabled_on_ios": true,
        "flag_new_game": true,
        "game_type_code": "live_dealer"
    },
    {
        "game_platform_id": "6112",
        "game_name": "_json:{\"1\":\"Niuniu\",\"2\":\"Niuniu\",\"3\":\"Niuniu\",\"4\":\"Niuniu\",\"5\":\"Niuniu\"}",
        "game_code": "niuniu",
        "progressive": false,
        "dlc_enabled": 0,
        "flash_enabled": 0,
        "offline_enabled": 0,
        "mobile_enabled": true,
        "note": null,
        "status": true,
        "flag_show_in_site": true,
        "no_cash_back": false,
        "void_bet": false,
        "attributes": null,
        "game_order": null,
        "html_five_enabled": true,
        "english_name": "Niuniu",
        "external_game_id": "niuniu",
        "clientid": null,
        "moduleid": null,
        "related_game_desc_id": null,
        "enabled_freespin": 0,
        "sub_game_provider": null,
        "enabled_on_android": true,
        "enabled_on_ios": true,
        "flag_new_game": true,
        "game_type_code": "live_dealer"
    },
    {
        "game_platform_id": "6112",
        "game_name": "_json:{\"1\":\"Oglok\",\"2\":\"Oglok\",\"3\":\"Oglok\",\"4\":\"Oglok\",\"5\":\"Oglok\"}",
        "game_code": "oglok",
        "progressive": false,
        "dlc_enabled": 0,
        "flash_enabled": 0,
        "offline_enabled": 0,
        "mobile_enabled": true,
        "note": null,
        "status": true,
        "flag_show_in_site": true,
        "no_cash_back": false,
        "void_bet": false,
        "attributes": null,
        "game_order": null,
        "html_five_enabled": true,
        "english_name": "Oglok",
        "external_game_id": "oglok",
        "clientid": null,
        "moduleid": null,
        "related_game_desc_id": null,
        "enabled_freespin": 0,
        "sub_game_provider": null,
        "enabled_on_android": true,
        "enabled_on_ios": true,
        "flag_new_game": true,
        "game_type_code": "live_dealer"
    },
    {
        "game_platform_id": "6112",
        "game_name": "_json:{\"1\":\"Poker Dice\",\"2\":\"Poker Dice\",\"3\":\"Poker Dice\",\"4\":\"Poker Dice\",\"5\":\"Poker Dice\"}",
        "game_code": "pokerdice",
        "progressive": false,
        "dlc_enabled": 0,
        "flash_enabled": 0,
        "offline_enabled": 0,
        "mobile_enabled": true,
        "note": null,
        "status": true,
        "flag_show_in_site": true,
        "no_cash_back": false,
        "void_bet": false,
        "attributes": null,
        "game_order": null,
        "html_five_enabled": true,
        "english_name": "Poker Dice",
        "external_game_id": "pokerdice",
        "clientid": null,
        "moduleid": null,
        "related_game_desc_id": null,
        "enabled_freespin": 0,
        "sub_game_provider": null,
        "enabled_on_android": true,
        "enabled_on_ios": true,
        "flag_new_game": true,
        "game_type_code": "live_dealer"
    },
    {
        "game_platform_id": "6112",
        "game_name": "_json:{\"1\":\"Red White\",\"2\":\"Red White\",\"3\":\"Red White\",\"4\":\"Red White\",\"5\":\"Red White\"}",
        "game_code": "redwhite",
        "progressive": false,
        "dlc_enabled": 0,
        "flash_enabled": 0,
        "offline_enabled": 0,
        "mobile_enabled": true,
        "note": null,
        "status": true,
        "flag_show_in_site": true,
        "no_cash_back": false,
        "void_bet": false,
        "attributes": null,
        "game_order": null,
        "html_five_enabled": true,
        "english_name": "Red White",
        "external_game_id": "redwhite",
        "clientid": null,
        "moduleid": null,
        "related_game_desc_id": null,
        "enabled_freespin": 0,
        "sub_game_provider": null,
        "enabled_on_android": true,
        "enabled_on_ios": true,
        "flag_new_game": true,
        "game_type_code": "live_dealer"
    },
    {
        "game_platform_id": "6112",
        "game_name": "_json:{\"1\":\"Roulette\",\"2\":\"Roulette\",\"3\":\"Roulette\",\"4\":\"Roulette\",\"5\":\"Roulette\"}",
        "game_code": "rl",
        "progressive": false,
        "dlc_enabled": 0,
        "flash_enabled": 0,
        "offline_enabled": 0,
        "mobile_enabled": true,
        "note": null,
        "status": true,
        "flag_show_in_site": true,
        "no_cash_back": false,
        "void_bet": false,
        "attributes": null,
        "game_order": null,
        "html_five_enabled": true,
        "english_name": "Roulette",
        "external_game_id": "rl",
        "clientid": null,
        "moduleid": null,
        "related_game_desc_id": null,
        "enabled_freespin": 0,
        "sub_game_provider": null,
        "enabled_on_android": true,
        "enabled_on_ios": true,
        "flag_new_game": true,
        "game_type_code": "live_dealer"
    },
    {
        "game_platform_id": "6112",
        "game_name": "_json:{\"1\":\"Roulette B\",\"2\":\"Roulette B\",\"3\":\"Roulette B\",\"4\":\"Roulette B\",\"5\":\"Roulette B\"}",
        "game_code": "rlb",
        "progressive": false,
        "dlc_enabled": 0,
        "flash_enabled": 0,
        "offline_enabled": 0,
        "mobile_enabled": true,
        "note": null,
        "status": true,
        "flag_show_in_site": true,
        "no_cash_back": false,
        "void_bet": false,
        "attributes": null,
        "game_order": null,
        "html_five_enabled": true,
        "english_name": "Roulette B",
        "external_game_id": "rlb",
        "clientid": null,
        "moduleid": null,
        "related_game_desc_id": null,
        "enabled_freespin": 0,
        "sub_game_provider": null,
        "enabled_on_android": true,
        "enabled_on_ios": true,
        "flag_new_game": true,
        "game_type_code": "live_dealer"
    },
    {
        "game_platform_id": "6112",
        "game_name": "_json:{\"1\":\"Roulette E\",\"2\":\"Roulette E\",\"3\":\"Roulette E\",\"4\":\"Roulette E\",\"5\":\"Roulette E\"}",
        "game_code": "rle",
        "progressive": false,
        "dlc_enabled": 0,
        "flash_enabled": 0,
        "offline_enabled": 0,
        "mobile_enabled": true,
        "note": null,
        "status": true,
        "flag_show_in_site": true,
        "no_cash_back": false,
        "void_bet": false,
        "attributes": null,
        "game_order": null,
        "html_five_enabled": true,
        "english_name": "Roulette E",
        "external_game_id": "rle",
        "clientid": null,
        "moduleid": null,
        "related_game_desc_id": null,
        "enabled_freespin": 0,
        "sub_game_provider": null,
        "enabled_on_android": true,
        "enabled_on_ios": true,
        "flag_new_game": true,
        "game_type_code": "live_dealer"
    },
    {
        "game_platform_id": "6112",
        "game_name": "_json:{\"1\":\"Roulette Europe\",\"2\":\"Roulette Europe\",\"3\":\"Roulette Europe\",\"4\":\"Roulette Europe\",\"5\":\"Roulette Europe\"}",
        "game_code": "rld",
        "progressive": false,
        "dlc_enabled": 0,
        "flash_enabled": 0,
        "offline_enabled": 0,
        "mobile_enabled": true,
        "note": null,
        "status": true,
        "flag_show_in_site": true,
        "no_cash_back": false,
        "void_bet": false,
        "attributes": null,
        "game_order": null,
        "html_five_enabled": true,
        "english_name": "Roulette Europe",
        "external_game_id": "rld",
        "clientid": null,
        "moduleid": null,
        "related_game_desc_id": null,
        "enabled_freespin": 0,
        "sub_game_provider": null,
        "enabled_on_android": true,
        "enabled_on_ios": true,
        "flag_new_game": true,
        "game_type_code": "live_dealer"
    },
    {
        "game_platform_id": "6112",
        "game_name": "_json:{\"1\":\"Roulette Lobby\",\"2\":\"Roulette Lobby\",\"3\":\"Roulette Lobby\",\"4\":\"Roulette Lobby\",\"5\":\"Roulette Lobby\"}",
        "game_code": "roulette-lobby",
        "progressive": false,
        "dlc_enabled": 0,
        "flash_enabled": 0,
        "offline_enabled": 0,
        "mobile_enabled": true,
        "note": null,
        "status": true,
        "flag_show_in_site": true,
        "no_cash_back": false,
        "void_bet": false,
        "attributes": null,
        "game_order": null,
        "html_five_enabled": true,
        "english_name": "Roulette Lobby",
        "external_game_id": "roulette-lobby",
        "clientid": null,
        "moduleid": null,
        "related_game_desc_id": null,
        "enabled_freespin": 0,
        "sub_game_provider": null,
        "enabled_on_android": true,
        "enabled_on_ios": true,
        "flag_new_game": true,
        "game_type_code": "live_dealer"
    },
    {
        "game_platform_id": "6112",
        "game_name": "_json:{\"1\":\"Shio Fights\",\"2\":\"Shio Fights\",\"3\":\"Shio Fights\",\"4\":\"Shio Fights\",\"5\":\"Shio Fights\"}",
        "game_code": "shiofights",
        "progressive": false,
        "dlc_enabled": 0,
        "flash_enabled": 0,
        "offline_enabled": 0,
        "mobile_enabled": true,
        "note": null,
        "status": true,
        "flag_show_in_site": true,
        "no_cash_back": false,
        "void_bet": false,
        "attributes": null,
        "game_order": null,
        "html_five_enabled": true,
        "english_name": "Shio Fights",
        "external_game_id": "shiofights",
        "clientid": null,
        "moduleid": null,
        "related_game_desc_id": null,
        "enabled_freespin": 0,
        "sub_game_provider": null,
        "enabled_on_android": true,
        "enabled_on_ios": true,
        "flag_new_game": true,
        "game_type_code": "live_dealer"
    },
    {
        "game_platform_id": "6112",
        "game_name": "_json:{\"1\":\"Sicbo Ball\",\"2\":\"Sicbo Ball\",\"3\":\"Sicbo Ball\",\"4\":\"Sicbo Ball\",\"5\":\"Sicbo Ball\"}",
        "game_code": "3d",
        "progressive": false,
        "dlc_enabled": 0,
        "flash_enabled": 0,
        "offline_enabled": 0,
        "mobile_enabled": true,
        "note": null,
        "status": true,
        "flag_show_in_site": true,
        "no_cash_back": false,
        "void_bet": false,
        "attributes": null,
        "game_order": null,
        "html_five_enabled": true,
        "english_name": "Sicbo Ball",
        "external_game_id": "3d",
        "clientid": null,
        "moduleid": null,
        "related_game_desc_id": null,
        "enabled_freespin": 0,
        "sub_game_provider": null,
        "enabled_on_android": true,
        "enabled_on_ios": true,
        "flag_new_game": true,
        "game_type_code": "live_dealer"
    },
    {
        "game_platform_id": "6112",
        "game_name": "_json:{\"1\":\"Sicbo Dice\",\"2\":\"Sicbo Dice\",\"3\":\"Sicbo Dice\",\"4\":\"Sicbo Dice\",\"5\":\"Sicbo Dice\"}",
        "game_code": "sicbodice",
        "progressive": false,
        "dlc_enabled": 0,
        "flash_enabled": 0,
        "offline_enabled": 0,
        "mobile_enabled": true,
        "note": null,
        "status": true,
        "flag_show_in_site": true,
        "no_cash_back": false,
        "void_bet": false,
        "attributes": null,
        "game_order": null,
        "html_five_enabled": true,
        "english_name": "Sicbo Dice",
        "external_game_id": "sicbodice",
        "clientid": null,
        "moduleid": null,
        "related_game_desc_id": null,
        "enabled_freespin": 0,
        "sub_game_provider": null,
        "enabled_on_android": true,
        "enabled_on_ios": true,
        "flag_new_game": true,
        "game_type_code": "live_dealer"
    },
    {
        "game_platform_id": "6112",
        "game_name": "_json:{\"1\":\"Suwit\",\"2\":\"Suwit\",\"3\":\"Suwit\",\"4\":\"Suwit\",\"5\":\"Suwit\"}",
        "game_code": "suwit",
        "progressive": false,
        "dlc_enabled": 0,
        "flash_enabled": 0,
        "offline_enabled": 0,
        "mobile_enabled": true,
        "note": null,
        "status": true,
        "flag_show_in_site": true,
        "no_cash_back": false,
        "void_bet": false,
        "attributes": null,
        "game_order": null,
        "html_five_enabled": true,
        "english_name": "Suwit",
        "external_game_id": "suwit",
        "clientid": null,
        "moduleid": null,
        "related_game_desc_id": null,
        "enabled_freespin": 0,
        "sub_game_provider": null,
        "enabled_on_android": true,
        "enabled_on_ios": true,
        "flag_new_game": true,
        "game_type_code": "live_dealer"
    }
]