[
    {
        "game_platform_id": "307",
        "game_name": "_json:{\"1\":\"UNKNOWN GAME\",\"2\":\"\u4e0d\u660e\u6e38\u620f\",\"3\":\"UNKNOWN GAME\",\"4\":\"UNKNOWN GAME\",\"5\":\"UNKNOWN GAME\"}",
        "game_code": "unknown",
        "dlc_enabled": "0",
        "progressive": "0",
        "flash_enabled": "1",
        "offline_enabled": "0",
        "mobile_enabled": "0",
        "note": null,
        "status": "1",
        "flag_show_in_site": "0",
        "no_cash_back": "0",
        "void_bet": "0",
        "attributes": null,
        "game_order": null,
        "html_five_enabled": "0",
        "english_name": "UNKNOWN GAME",
        "external_game_id": "unknown",
        "clientid": null,
        "moduleid": null,
        "related_game_desc_id": null,
        "enabled_freespin": "0",
        "sub_game_provider": null,
        "enabled_on_android": "0",
        "enabled_on_ios": "0",
        "flag_new_game": "0",
        "demo_link": null,
        "game_type_code": "unknown"
    },
    {
        "game_platform_id": "307",
        "game_name": "_json:{\"1\":\"Fish Hunter King\",\"2\":\"\u6355\u9c7c\u738b\",\"3\":\"Fish Hunter King\",\"4\":\"Fish Hunter King\",\"5\":\"Fish Hunter King\"}",
        "game_code": "BUYU",
        "dlc_enabled": "0",
        "progressive": "0",
        "flash_enabled": "1",
        "offline_enabled": "0",
        "mobile_enabled": "0",
        "note": null,
        "status": "1",
        "flag_show_in_site": "1",
        "no_cash_back": "0",
        "void_bet": "0",
        "attributes": null,
        "game_order": null,
        "html_five_enabled": "1",
        "english_name": "Fish Hunter King",
        "external_game_id": "BUYU",
        "clientid": null,
        "moduleid": null,
        "related_game_desc_id": null,
        "enabled_freespin": "0",
        "sub_game_provider": null,
        "enabled_on_android": "0",
        "enabled_on_ios": "0",
        "flag_new_game": "0",
        "demo_link": null,
        "game_type_code": "others"
    },
    {
        "game_platform_id": "307",
        "game_name": "_json:{\"1\":\"AGIN\",\"2\":\"AG \u56fd\u9645\u6e38\u620f\u5385\",\"3\":\"AGIN\",\"4\":\"AGIN\",\"5\":\"AGIN\"}",
        "game_code": "AGIN",
        "dlc_enabled": "0",
        "progressive": "0",
        "flash_enabled": "1",
        "offline_enabled": "0",
        "mobile_enabled": "0",
        "note": null,
        "status": "1",
        "flag_show_in_site": "1",
        "no_cash_back": "0",
        "void_bet": "0",
        "attributes": null,
        "game_order": null,
        "html_five_enabled": "1",
        "english_name": "AGIN",
        "external_game_id": "AGIN",
        "clientid": null,
        "moduleid": null,
        "related_game_desc_id": null,
        "enabled_freespin": "0",
        "sub_game_provider": null,
        "enabled_on_android": "0",
        "enabled_on_ios": "0",
        "flag_new_game": "0",
        "demo_link": null,
        "game_type_code": "others"
    },
    {
        "game_platform_id": "307",
        "game_name": "_json:{\"1\":\"Mark Six\",\"2\":\"\u516d\u5408\u5f69\",\"3\":\"Mark Six\",\"4\":\"Mark Six\",\"5\":\"Mark Six\"}",
        "game_code": "liuhecai",
        "dlc_enabled": "0",
        "progressive": "0",
        "flash_enabled": "1",
        "offline_enabled": "0",
        "mobile_enabled": "0",
        "note": null,
        "status": "1",
        "flag_show_in_site": "1",
        "no_cash_back": "0",
        "void_bet": "0",
        "attributes": null,
        "game_order": null,
        "html_five_enabled": "1",
        "english_name": "Mark Six",
        "external_game_id": "liuhecai",
        "clientid": null,
        "moduleid": null,
        "related_game_desc_id": null,
        "enabled_freespin": "0",
        "sub_game_provider": null,
        "enabled_on_android": "0",
        "enabled_on_ios": "0",
        "flag_new_game": "0",
        "demo_link": null,
        "game_type_code": "lottery"
    },
    {
        "game_platform_id": "307",
        "game_name": "_json:{\"1\":\"Lotto 3D\",\"2\":\"\u798f\u5f69 3d\",\"3\":\"Lotto 3D\",\"4\":\"Lotto 3D\",\"5\":\"Lotto 3D\"}",
        "game_code": "fc3d",
        "dlc_enabled": "0",
        "progressive": "0",
        "flash_enabled": "1",
        "offline_enabled": "0",
        "mobile_enabled": "0",
        "note": null,
        "status": "1",
        "flag_show_in_site": "1",
        "no_cash_back": "0",
        "void_bet": "0",
        "attributes": null,
        "game_order": null,
        "html_five_enabled": "1",
        "english_name": "Lotto 3D",
        "external_game_id": "fc3d",
        "clientid": null,
        "moduleid": null,
        "related_game_desc_id": null,
        "enabled_freespin": "0",
        "sub_game_provider": null,
        "enabled_on_android": "0",
        "enabled_on_ios": "0",
        "flag_new_game": "0",
        "demo_link": null,
        "game_type_code": "lottery"
    },
    {
        "game_platform_id": "307",
        "game_name": "_json:{\"1\":\"Sports Lotto\",\"2\":\"\u6392\u5217 3\",\"3\":\"Sports Lotto\",\"4\":\"Sports Lotto\",\"5\":\"Sports Lotto\"}",
        "game_code": "pailie3",
        "dlc_enabled": "0",
        "progressive": "0",
        "flash_enabled": "1",
        "offline_enabled": "0",
        "mobile_enabled": "0",
        "note": null,
        "status": "1",
        "flag_show_in_site": "1",
        "no_cash_back": "0",
        "void_bet": "0",
        "attributes": null,
        "game_order": null,
        "html_five_enabled": "1",
        "english_name": "Sports Lotto",
        "external_game_id": "pailie3",
        "clientid": null,
        "moduleid": null,
        "related_game_desc_id": null,
        "enabled_freespin": "0",
        "sub_game_provider": null,
        "enabled_on_android": "0",
        "enabled_on_ios": "0",
        "flag_new_game": "0",
        "demo_link": null,
        "game_type_code": "lottery"
    },
    {
        "game_platform_id": "307",
        "game_name": "_json:{\"1\":\"Seven Color\",\"2\":\"\u4e03\u661f\u5f69\",\"3\":\"Seven Color\",\"4\":\"Seven Color\",\"5\":\"Seven Color\"}",
        "game_code": "qixing",
        "dlc_enabled": "0",
        "progressive": "0",
        "flash_enabled": "1",
        "offline_enabled": "0",
        "mobile_enabled": "0",
        "note": null,
        "status": "1",
        "flag_show_in_site": "1",
        "no_cash_back": "0",
        "void_bet": "0",
        "attributes": null,
        "game_order": null,
        "html_five_enabled": "1",
        "english_name": "Seven Color",
        "external_game_id": "qixing",
        "clientid": null,
        "moduleid": null,
        "related_game_desc_id": null,
        "enabled_freespin": "0",
        "sub_game_provider": null,
        "enabled_on_android": "0",
        "enabled_on_ios": "0",
        "flag_new_game": "0",
        "demo_link": null,
        "game_type_code": "lottery"
    },
    {
        "game_platform_id": "307",
        "game_name": "_json:{\"1\":\"Chongqing Lotto\",\"2\":\"\u91cd\u5e86\u65f6\u65f6\u5f69\",\"3\":\"Chongqing Lotto\",\"4\":\"Chongqing Lotto\",\"5\":\"Chongqing Lotto\"}",
        "game_code": "cqshishicai",
        "dlc_enabled": "0",
        "progressive": "0",
        "flash_enabled": "1",
        "offline_enabled": "0",
        "mobile_enabled": "0",
        "note": null,
        "status": "1",
        "flag_show_in_site": "1",
        "no_cash_back": "0",
        "void_bet": "0",
        "attributes": null,
        "game_order": null,
        "html_five_enabled": "1",
        "english_name": "Chongqing Lotto",
        "external_game_id": "cqshishicai",
        "clientid": null,
        "moduleid": null,
        "related_game_desc_id": null,
        "enabled_freespin": "0",
        "sub_game_provider": null,
        "enabled_on_android": "0",
        "enabled_on_ios": "0",
        "flag_new_game": "0",
        "demo_link": null,
        "game_type_code": "lottery"
    },
    {
        "game_platform_id": "307",
        "game_name": "_json:{\"1\":\"Tianjin Lotto\",\"2\":\"\u5929\u6d25\u65f6\u65f6\u5f69\",\"3\":\"Tianjin Lotto\",\"4\":\"Tianjin Lotto\",\"5\":\"Tianjin Lotto\"}",
        "game_code": "tjshishicai",
        "dlc_enabled": "0",
        "progressive": "0",
        "flash_enabled": "1",
        "offline_enabled": "0",
        "mobile_enabled": "0",
        "note": null,
        "status": "1",
        "flag_show_in_site": "1",
        "no_cash_back": "0",
        "void_bet": "0",
        "attributes": null,
        "game_order": null,
        "html_five_enabled": "1",
        "english_name": "Tianjin Lotto",
        "external_game_id": "tjshishicai",
        "clientid": null,
        "moduleid": null,
        "related_game_desc_id": null,
        "enabled_freespin": "0",
        "sub_game_provider": null,
        "enabled_on_android": "0",
        "enabled_on_ios": "0",
        "flag_new_game": "0",
        "demo_link": null,
        "game_type_code": "lottery"
    },
    {
        "game_platform_id": "307",
        "game_name": "_json:{\"1\":\"Jiangxi Lotto\",\"2\":\"\u6c5f\u897f\u65f6\u65f6\u5f69\",\"3\":\"Jiangxi Lotto\",\"4\":\"Jiangxi Lotto\",\"5\":\"Jiangxi Lotto\"}",
        "game_code": "jxshishicai",
        "dlc_enabled": "0",
        "progressive": "0",
        "flash_enabled": "1",
        "offline_enabled": "0",
        "mobile_enabled": "0",
        "note": null,
        "status": "1",
        "flag_show_in_site": "1",
        "no_cash_back": "0",
        "void_bet": "0",
        "attributes": null,
        "game_order": null,
        "html_five_enabled": "1",
        "english_name": "Jiangxi Lotto",
        "external_game_id": "jxshishicai",
        "clientid": null,
        "moduleid": null,
        "related_game_desc_id": null,
        "enabled_freespin": "0",
        "sub_game_provider": null,
        "enabled_on_android": "0",
        "enabled_on_ios": "0",
        "flag_new_game": "0",
        "demo_link": null,
        "game_type_code": "lottery"
    },
    {
        "game_platform_id": "307",
        "game_name": "_json:{\"1\":\"Xinjiang Lotto\",\"2\":\"\u65b0\u7586\u65f6\u65f6\u5f69\",\"3\":\"Xinjiang Lotto\",\"4\":\"Xinjiang Lotto\",\"5\":\"Xinjiang Lotto\"}",
        "game_code": "xjshishicai",
        "dlc_enabled": "0",
        "progressive": "0",
        "flash_enabled": "1",
        "offline_enabled": "0",
        "mobile_enabled": "0",
        "note": null,
        "status": "1",
        "flag_show_in_site": "1",
        "no_cash_back": "0",
        "void_bet": "0",
        "attributes": null,
        "game_order": null,
        "html_five_enabled": "1",
        "english_name": "Xinjiang Lotto",
        "external_game_id": "xjshishicai",
        "clientid": null,
        "moduleid": null,
        "related_game_desc_id": null,
        "enabled_freespin": "0",
        "sub_game_provider": null,
        "enabled_on_android": "0",
        "enabled_on_ios": "0",
        "flag_new_game": "0",
        "demo_link": null,
        "game_type_code": "lottery"
    },
    {
        "game_platform_id": "307",
        "game_name": "_json:{\"1\":\"Guangxi Happy 10\",\"2\":\"\u5e7f\u897f\u5feb\u4e50\u5341\u5206\",\"3\":\"Guangxi Happy 10\",\"4\":\"Guangxi Happy 10\",\"5\":\"Guangxi Happy 10\"}",
        "game_code": "gxkuaile10",
        "dlc_enabled": "0",
        "progressive": "0",
        "flash_enabled": "1",
        "offline_enabled": "0",
        "mobile_enabled": "0",
        "note": null,
        "status": "1",
        "flag_show_in_site": "1",
        "no_cash_back": "0",
        "void_bet": "0",
        "attributes": null,
        "game_order": null,
        "html_five_enabled": "1",
        "english_name": "Guangxi Happy 10",
        "external_game_id": "gxkuaile10",
        "clientid": null,
        "moduleid": null,
        "related_game_desc_id": null,
        "enabled_freespin": "0",
        "sub_game_provider": null,
        "enabled_on_android": "0",
        "enabled_on_ios": "0",
        "flag_new_game": "0",
        "demo_link": null,
        "game_type_code": "lottery"
    },
    {
        "game_platform_id": "307",
        "game_name": "_json:{\"1\":\"Guangxi Happy 10\",\"2\":\"\u5e7f\u4e1c\u5feb\u4e50\u5341\u5206\",\"3\":\"Guangxi Happy 10\",\"4\":\"Guangxi Happy 10\",\"5\":\"Guangxi Happy 10\"}",
        "game_code": "gdkuaile10",
        "dlc_enabled": "0",
        "progressive": "0",
        "flash_enabled": "1",
        "offline_enabled": "0",
        "mobile_enabled": "0",
        "note": null,
        "status": "1",
        "flag_show_in_site": "1",
        "no_cash_back": "0",
        "void_bet": "0",
        "attributes": null,
        "game_order": null,
        "html_five_enabled": "1",
        "english_name": "Guangxi Happy 10",
        "external_game_id": "gdkuaile10",
        "clientid": null,
        "moduleid": null,
        "related_game_desc_id": null,
        "enabled_freespin": "0",
        "sub_game_provider": null,
        "enabled_on_android": "0",
        "enabled_on_ios": "0",
        "flag_new_game": "0",
        "demo_link": null,
        "game_type_code": "lottery"
    },
    {
        "game_platform_id": "307",
        "game_name": "_json:{\"1\":\"Chongqing Happy 10\",\"2\":\"\u91cd\u5e86\u5feb\u4e50\u5341\u5206\",\"3\":\"Chongqing Happy 10\",\"4\":\"Chongqing Happy 10\",\"5\":\"Chongqing Happy 10\"}",
        "game_code": "cqkuaile10",
        "dlc_enabled": "0",
        "progressive": "0",
        "flash_enabled": "1",
        "offline_enabled": "0",
        "mobile_enabled": "0",
        "note": null,
        "status": "1",
        "flag_show_in_site": "1",
        "no_cash_back": "0",
        "void_bet": "0",
        "attributes": null,
        "game_order": null,
        "html_five_enabled": "1",
        "english_name": "Chongqing Happy 10",
        "external_game_id": "cqkuaile10",
        "clientid": null,
        "moduleid": null,
        "related_game_desc_id": null,
        "enabled_freespin": "0",
        "sub_game_provider": null,
        "enabled_on_android": "0",
        "enabled_on_ios": "0",
        "flag_new_game": "0",
        "demo_link": null,
        "game_type_code": "lottery"
    },
    {
        "game_platform_id": "307",
        "game_name": "_json:{\"1\":\"Tianjin Happy 10\",\"2\":\"\u5929\u6d25\u5feb\u4e50\u5341\u5206\",\"3\":\"Tianjin Happy 10\",\"4\":\"Tianjin Happy 10\",\"5\":\"Tianjin Happy 10\"}",
        "game_code": "tjkuaile10",
        "dlc_enabled": "0",
        "progressive": "0",
        "flash_enabled": "1",
        "offline_enabled": "0",
        "mobile_enabled": "0",
        "note": null,
        "status": "1",
        "flag_show_in_site": "1",
        "no_cash_back": "0",
        "void_bet": "0",
        "attributes": null,
        "game_order": null,
        "html_five_enabled": "1",
        "english_name": "Tianjin Happy 10",
        "external_game_id": "tjkuaile10",
        "clientid": null,
        "moduleid": null,
        "related_game_desc_id": null,
        "enabled_freespin": "0",
        "sub_game_provider": null,
        "enabled_on_android": "0",
        "enabled_on_ios": "0",
        "flag_new_game": "0",
        "demo_link": null,
        "game_type_code": "lottery"
    },
    {
        "game_platform_id": "307",
        "game_name": "_json:{\"1\":\"Guangdong 11\/5\",\"2\":\"\u5e7f\u4e1c 11 \u9009 5\",\"3\":\"Guangdong 11\/5\",\"4\":\"Guangdong 11\/5\",\"5\":\"Guangdong 11\/5\"}",
        "game_code": "gd11xuan5",
        "dlc_enabled": "0",
        "progressive": "0",
        "flash_enabled": "1",
        "offline_enabled": "0",
        "mobile_enabled": "0",
        "note": null,
        "status": "1",
        "flag_show_in_site": "1",
        "no_cash_back": "0",
        "void_bet": "0",
        "attributes": null,
        "game_order": null,
        "html_five_enabled": "1",
        "english_name": "Guangdong 11\/5",
        "external_game_id": "gd11xuan5",
        "clientid": null,
        "moduleid": null,
        "related_game_desc_id": null,
        "enabled_freespin": "0",
        "sub_game_provider": null,
        "enabled_on_android": "0",
        "enabled_on_ios": "0",
        "flag_new_game": "0",
        "demo_link": null,
        "game_type_code": "lottery"
    },
    {
        "game_platform_id": "307",
        "game_name": "_json:{\"1\":\"Jiangxi 11\/5\",\"2\":\"\u6c5f\u897f 11 \u9009 5\",\"3\":\"Jiangxi 11\/5\",\"4\":\"Jiangxi 11\/5\",\"5\":\"Jiangxi 11\/5\"}",
        "game_code": "jx11xuan5",
        "dlc_enabled": "0",
        "progressive": "0",
        "flash_enabled": "1",
        "offline_enabled": "0",
        "mobile_enabled": "0",
        "note": null,
        "status": "1",
        "flag_show_in_site": "1",
        "no_cash_back": "0",
        "void_bet": "0",
        "attributes": null,
        "game_order": null,
        "html_five_enabled": "1",
        "english_name": "Jiangxi 11\/5",
        "external_game_id": "jx11xuan5",
        "clientid": null,
        "moduleid": null,
        "related_game_desc_id": null,
        "enabled_freespin": "0",
        "sub_game_provider": null,
        "enabled_on_android": "0",
        "enabled_on_ios": "0",
        "flag_new_game": "0",
        "demo_link": null,
        "game_type_code": "lottery"
    },
    {
        "game_platform_id": "307",
        "game_name": "_json:{\"1\":\"Shandong 11\/5\",\"2\":\"\u5c71\u4e1c 11 \u9009 5\",\"3\":\"Shandong 11\/5\",\"4\":\"Shandong 11\/5\",\"5\":\"Shandong 11\/5\"}",
        "game_code": "sd11xuan5",
        "dlc_enabled": "0",
        "progressive": "0",
        "flash_enabled": "1",
        "offline_enabled": "0",
        "mobile_enabled": "0",
        "note": null,
        "status": "1",
        "flag_show_in_site": "1",
        "no_cash_back": "0",
        "void_bet": "0",
        "attributes": null,
        "game_order": null,
        "html_five_enabled": "1",
        "english_name": "Shandong 11\/5",
        "external_game_id": "sd11xuan5",
        "clientid": null,
        "moduleid": null,
        "related_game_desc_id": null,
        "enabled_freespin": "0",
        "sub_game_provider": null,
        "enabled_on_android": "0",
        "enabled_on_ios": "0",
        "flag_new_game": "0",
        "demo_link": null,
        "game_type_code": "lottery"
    },
    {
        "game_platform_id": "307",
        "game_name": "_json:{\"1\":\"Guizhou 11\/5\",\"2\":\"\u8d35\u5dde 11 \u9009 5\",\"3\":\"Guizhou 11\/5\",\"4\":\"Guizhou 11\/5\",\"5\":\"Guizhou 11\/5\"}",
        "game_code": "gz11xuan5",
        "dlc_enabled": "0",
        "progressive": "0",
        "flash_enabled": "1",
        "offline_enabled": "0",
        "mobile_enabled": "0",
        "note": null,
        "status": "1",
        "flag_show_in_site": "1",
        "no_cash_back": "0",
        "void_bet": "0",
        "attributes": null,
        "game_order": null,
        "html_five_enabled": "1",
        "english_name": "Guizhou 11\/5",
        "external_game_id": "gz11xuan5",
        "clientid": null,
        "moduleid": null,
        "related_game_desc_id": null,
        "enabled_freespin": "0",
        "sub_game_provider": null,
        "enabled_on_android": "0",
        "enabled_on_ios": "0",
        "flag_new_game": "0",
        "demo_link": null,
        "game_type_code": "lottery"
    },
    {
        "game_platform_id": "307",
        "game_name": "_json:{\"1\":\"Beijing PK10\",\"2\":\"\u5317\u4eac PK \u62fe\",\"3\":\"Beijing PK10\",\"4\":\"Beijing PK10\",\"5\":\"Beijing PK10\"}",
        "game_code": "bjpkshi",
        "dlc_enabled": "0",
        "progressive": "0",
        "flash_enabled": "1",
        "offline_enabled": "0",
        "mobile_enabled": "0",
        "note": null,
        "status": "1",
        "flag_show_in_site": "1",
        "no_cash_back": "0",
        "void_bet": "0",
        "attributes": null,
        "game_order": null,
        "html_five_enabled": "1",
        "english_name": "Beijing PK10",
        "external_game_id": "bjpkshi",
        "clientid": null,
        "moduleid": null,
        "related_game_desc_id": null,
        "enabled_freespin": "0",
        "sub_game_provider": null,
        "enabled_on_android": "0",
        "enabled_on_ios": "0",
        "flag_new_game": "0",
        "demo_link": null,
        "game_type_code": "lottery"
    },
    {
        "game_platform_id": "307",
        "game_name": "_json:{\"1\":\"Beijing Happy 8\",\"2\":\"\u5317\u4eac\u5feb\u4e50 8\",\"3\":\"Beijing Happy 8\",\"4\":\"Beijing Happy 8\",\"5\":\"Beijing Happy 8\"}",
        "game_code": "bjkuaile8",
        "dlc_enabled": "0",
        "progressive": "0",
        "flash_enabled": "1",
        "offline_enabled": "0",
        "mobile_enabled": "0",
        "note": null,
        "status": "1",
        "flag_show_in_site": "1",
        "no_cash_back": "0",
        "void_bet": "0",
        "attributes": null,
        "game_order": null,
        "html_five_enabled": "1",
        "english_name": "Beijing Happy 8",
        "external_game_id": "bjkuaile8",
        "clientid": null,
        "moduleid": null,
        "related_game_desc_id": null,
        "enabled_freespin": "0",
        "sub_game_provider": null,
        "enabled_on_android": "0",
        "enabled_on_ios": "0",
        "flag_new_game": "0",
        "demo_link": null,
        "game_type_code": "lottery"
    },
    {
        "game_platform_id": "307",
        "game_name": "_json:{\"1\":\"Guangxi Fast 3\",\"2\":\"\u5e7f\u897f\u5feb 3\",\"3\":\"Guangxi Fast 3\",\"4\":\"Guangxi Fast 3\",\"5\":\"Guangxi Fast 3\"}",
        "game_code": "gxkuai3",
        "dlc_enabled": "0",
        "progressive": "0",
        "flash_enabled": "1",
        "offline_enabled": "0",
        "mobile_enabled": "0",
        "note": null,
        "status": "1",
        "flag_show_in_site": "1",
        "no_cash_back": "0",
        "void_bet": "0",
        "attributes": null,
        "game_order": null,
        "html_five_enabled": "1",
        "english_name": "Guangxi Fast 3",
        "external_game_id": "gxkuai3",
        "clientid": null,
        "moduleid": null,
        "related_game_desc_id": null,
        "enabled_freespin": "0",
        "sub_game_provider": null,
        "enabled_on_android": "0",
        "enabled_on_ios": "0",
        "flag_new_game": "0",
        "demo_link": null,
        "game_type_code": "lottery"
    },
    {
        "game_platform_id": "307",
        "game_name": "_json:{\"1\":\"Jilin Fast 3\",\"2\":\"\u5409\u6797\u5feb 3\",\"3\":\"Jilin Fast 3\",\"4\":\"Jilin Fast 3\",\"5\":\"Jilin Fast 3\"}",
        "game_code": "jilin_kuai3",
        "dlc_enabled": "0",
        "progressive": "0",
        "flash_enabled": "1",
        "offline_enabled": "0",
        "mobile_enabled": "0",
        "note": null,
        "status": "1",
        "flag_show_in_site": "1",
        "no_cash_back": "0",
        "void_bet": "0",
        "attributes": null,
        "game_order": null,
        "html_five_enabled": "1",
        "english_name": "Jilin Fast 3",
        "external_game_id": "jilin_kuai3",
        "clientid": null,
        "moduleid": null,
        "related_game_desc_id": null,
        "enabled_freespin": "0",
        "sub_game_provider": null,
        "enabled_on_android": "0",
        "enabled_on_ios": "0",
        "flag_new_game": "0",
        "demo_link": null,
        "game_type_code": "lottery"
    },
    {
        "game_platform_id": "307",
        "game_name": "_json:{\"1\":\"Anhui Sic Bo\",\"2\":\"\u5b89\u5fbd\u9ab0\u5b9d\",\"3\":\"Anhui Sic Bo\",\"4\":\"Anhui Sic Bo\",\"5\":\"Anhui Sic Bo\"}",
        "game_code": "ahkuai3",
        "dlc_enabled": "0",
        "progressive": "0",
        "flash_enabled": "1",
        "offline_enabled": "0",
        "mobile_enabled": "0",
        "note": null,
        "status": "1",
        "flag_show_in_site": "1",
        "no_cash_back": "0",
        "void_bet": "0",
        "attributes": null,
        "game_order": null,
        "html_five_enabled": "1",
        "english_name": "Anhui Sic Bo",
        "external_game_id": "ahkuai3",
        "clientid": null,
        "moduleid": null,
        "related_game_desc_id": null,
        "enabled_freespin": "0",
        "sub_game_provider": null,
        "enabled_on_android": "0",
        "enabled_on_ios": "0",
        "flag_new_game": "0",
        "demo_link": null,
        "game_type_code": "lottery"
    },
    {
        "game_platform_id": "307",
        "game_name": "_json:{\"1\":\"Jiangsu Sic Bo\",\"2\":\"\u6c5f\u82cf\u9ab0\u5b9d\",\"3\":\"Jiangsu Sic Bo\",\"4\":\"Jiangsu Sic Bo\",\"5\":\"Jiangsu Sic Bo\"}",
        "game_code": "jskuai3",
        "dlc_enabled": "0",
        "progressive": "0",
        "flash_enabled": "1",
        "offline_enabled": "0",
        "mobile_enabled": "0",
        "note": null,
        "status": "1",
        "flag_show_in_site": "1",
        "no_cash_back": "0",
        "void_bet": "0",
        "attributes": null,
        "game_order": null,
        "html_five_enabled": "1",
        "english_name": "Jiangsu Sic Bo",
        "external_game_id": "jskuai3",
        "clientid": null,
        "moduleid": null,
        "related_game_desc_id": null,
        "enabled_freespin": "0",
        "sub_game_provider": null,
        "enabled_on_android": "0",
        "enabled_on_ios": "0",
        "flag_new_game": "0",
        "demo_link": null,
        "game_type_code": "lottery"
    },
    {
        "game_platform_id": "307",
        "game_name": "_json:{\"1\":\"Hubei Sic Bo\",\"2\":\"\u6e56\u5317\u9ab0\u5b9d\",\"3\":\"Hubei Sic Bo\",\"4\":\"Hubei Sic Bo\",\"5\":\"Hubei Sic Bo\"}",
        "game_code": "hubei_shaibao",
        "dlc_enabled": "0",
        "progressive": "0",
        "flash_enabled": "1",
        "offline_enabled": "0",
        "mobile_enabled": "0",
        "note": null,
        "status": "1",
        "flag_show_in_site": "1",
        "no_cash_back": "0",
        "void_bet": "0",
        "attributes": null,
        "game_order": null,
        "html_five_enabled": "1",
        "english_name": "Hubei Sic Bo",
        "external_game_id": "hubei_shaibao",
        "clientid": null,
        "moduleid": null,
        "related_game_desc_id": null,
        "enabled_freespin": "0",
        "sub_game_provider": null,
        "enabled_on_android": "0",
        "enabled_on_ios": "0",
        "flag_new_game": "0",
        "demo_link": null,
        "game_type_code": "lottery"
    },
    {
        "game_platform_id": "307",
        "game_name": "_json:{\"1\":\"Hebei Sic Bo\",\"2\":\"\u6cb3\u5317\u9ab0\u5b9d\",\"3\":\"Hebei Sic Bo\",\"4\":\"Hebei Sic Bo\",\"5\":\"Hebei Sic Bo\"}",
        "game_code": "hebei_shaibao",
        "dlc_enabled": "0",
        "progressive": "0",
        "flash_enabled": "1",
        "offline_enabled": "0",
        "mobile_enabled": "0",
        "note": null,
        "status": "1",
        "flag_show_in_site": "1",
        "no_cash_back": "0",
        "void_bet": "0",
        "attributes": null,
        "game_order": null,
        "html_five_enabled": "1",
        "english_name": "Hebei Sic Bo",
        "external_game_id": "hebei_shaibao",
        "clientid": null,
        "moduleid": null,
        "related_game_desc_id": null,
        "enabled_freespin": "0",
        "sub_game_provider": null,
        "enabled_on_android": "0",
        "enabled_on_ios": "0",
        "flag_new_game": "0",
        "demo_link": null,
        "game_type_code": "lottery"
    },
    {
        "game_platform_id": "307",
        "game_name": "_json:{\"1\":\"Chongqing Lotto\",\"2\":\"\u91cd\u5e86\u65f6\u65f6\u5f69\",\"3\":\"Chongqing Lotto\",\"4\":\"Chongqing Lotto\",\"5\":\"Chongqing Lotto\"}",
        "game_code": "cqshishicai_gf",
        "dlc_enabled": "0",
        "progressive": "0",
        "flash_enabled": "1",
        "offline_enabled": "0",
        "mobile_enabled": "0",
        "note": null,
        "status": "1",
        "flag_show_in_site": "1",
        "no_cash_back": "0",
        "void_bet": "0",
        "attributes": null,
        "game_order": null,
        "html_five_enabled": "1",
        "english_name": "Chongqing Lotto",
        "external_game_id": "cqshishicai_gf",
        "clientid": null,
        "moduleid": null,
        "related_game_desc_id": null,
        "enabled_freespin": "0",
        "sub_game_provider": null,
        "enabled_on_android": "0",
        "enabled_on_ios": "0",
        "flag_new_game": "0",
        "demo_link": null,
        "game_type_code": "lottery"
    },
    {
        "game_platform_id": "307",
        "game_name": "_json:{\"1\":\"Tianjin Lotto\",\"2\":\"\u5929\u6d25\u65f6\u65f6\u5f69\",\"3\":\"Tianjin Lotto\",\"4\":\"Tianjin Lotto\",\"5\":\"Tianjin Lotto\"}",
        "game_code": "tjshishicai_gf",
        "dlc_enabled": "0",
        "progressive": "0",
        "flash_enabled": "1",
        "offline_enabled": "0",
        "mobile_enabled": "0",
        "note": null,
        "status": "1",
        "flag_show_in_site": "1",
        "no_cash_back": "0",
        "void_bet": "0",
        "attributes": null,
        "game_order": null,
        "html_five_enabled": "1",
        "english_name": "Tianjin Lotto",
        "external_game_id": "tjshishicai_gf",
        "clientid": null,
        "moduleid": null,
        "related_game_desc_id": null,
        "enabled_freespin": "0",
        "sub_game_provider": null,
        "enabled_on_android": "0",
        "enabled_on_ios": "0",
        "flag_new_game": "0",
        "demo_link": null,
        "game_type_code": "lottery"
    },
    {
        "game_platform_id": "307",
        "game_name": "_json:{\"1\":\"Xinjiang Lotto\",\"2\":\"\u65b0\u7586\u65f6\u65f6\u5f69\",\"3\":\"Xinjiang Lotto\",\"4\":\"Xinjiang Lotto\",\"5\":\"Xinjiang Lotto\"}",
        "game_code": "xjshishicai_gf",
        "dlc_enabled": "0",
        "progressive": "0",
        "flash_enabled": "1",
        "offline_enabled": "0",
        "mobile_enabled": "0",
        "note": null,
        "status": "1",
        "flag_show_in_site": "1",
        "no_cash_back": "0",
        "void_bet": "0",
        "attributes": null,
        "game_order": null,
        "html_five_enabled": "1",
        "english_name": "Xinjiang Lotto",
        "external_game_id": "xjshishicai_gf",
        "clientid": null,
        "moduleid": null,
        "related_game_desc_id": null,
        "enabled_freespin": "0",
        "sub_game_provider": null,
        "enabled_on_android": "0",
        "enabled_on_ios": "0",
        "flag_new_game": "0",
        "demo_link": null,
        "game_type_code": "lottery"
    },
    {
        "game_platform_id": "307",
        "game_name": "_json:{\"1\":\"Beijing PK10\",\"2\":\"\u5317\u4eac PK \u62fe\",\"3\":\"Beijing PK10\",\"4\":\"Beijing PK10\",\"5\":\"Beijing PK10\"}",
        "game_code": "bjpkshi_gf",
        "dlc_enabled": "0",
        "progressive": "0",
        "flash_enabled": "1",
        "offline_enabled": "0",
        "mobile_enabled": "0",
        "note": null,
        "status": "1",
        "flag_show_in_site": "1",
        "no_cash_back": "0",
        "void_bet": "0",
        "attributes": null,
        "game_order": null,
        "html_five_enabled": "1",
        "english_name": "Beijing PK10",
        "external_game_id": "bjpkshi_gf",
        "clientid": null,
        "moduleid": null,
        "related_game_desc_id": null,
        "enabled_freespin": "0",
        "sub_game_provider": null,
        "enabled_on_android": "0",
        "enabled_on_ios": "0",
        "flag_new_game": "0",
        "demo_link": null,
        "game_type_code": "lottery"
    },
    {
        "game_platform_id": "307",
        "game_name": "_json:{\"1\":\"Guangdong 11\/5\",\"2\":\"\u5e7f\u4e1c 11 \u9009 5\",\"3\":\"Guangdong 11\/5\",\"4\":\"Guangdong 11\/5\",\"5\":\"Guangdong 11\/5\"}",
        "game_code": "gd11xuan5_gf",
        "dlc_enabled": "0",
        "progressive": "0",
        "flash_enabled": "1",
        "offline_enabled": "0",
        "mobile_enabled": "0",
        "note": null,
        "status": "1",
        "flag_show_in_site": "1",
        "no_cash_back": "0",
        "void_bet": "0",
        "attributes": null,
        "game_order": null,
        "html_five_enabled": "1",
        "english_name": "Guangdong 11\/5",
        "external_game_id": "gd11xuan5_gf",
        "clientid": null,
        "moduleid": null,
        "related_game_desc_id": null,
        "enabled_freespin": "0",
        "sub_game_provider": null,
        "enabled_on_android": "0",
        "enabled_on_ios": "0",
        "flag_new_game": "0",
        "demo_link": null,
        "game_type_code": "lottery"
    },
    {
        "game_platform_id": "307",
        "game_name": "_json:{\"1\":\"Shandong 11\/5\",\"2\":\"\u5c71\u4e1c 11 \u9009 5\",\"3\":\"Shandong 11\/5\",\"4\":\"Shandong 11\/5\",\"5\":\"Shandong 11\/5\"}",
        "game_code": "sd11xuan5_gf",
        "dlc_enabled": "0",
        "progressive": "0",
        "flash_enabled": "1",
        "offline_enabled": "0",
        "mobile_enabled": "0",
        "note": null,
        "status": "1",
        "flag_show_in_site": "1",
        "no_cash_back": "0",
        "void_bet": "0",
        "attributes": null,
        "game_order": null,
        "html_five_enabled": "1",
        "english_name": "Shandong 11\/5",
        "external_game_id": "sd11xuan5_gf",
        "clientid": null,
        "moduleid": null,
        "related_game_desc_id": null,
        "enabled_freespin": "0",
        "sub_game_provider": null,
        "enabled_on_android": "0",
        "enabled_on_ios": "0",
        "flag_new_game": "0",
        "demo_link": null,
        "game_type_code": "lottery"
    },
    {
        "game_platform_id": "307",
        "game_name": "_json:{\"1\":\"Jiangxi 11\/5\",\"2\":\"\u6c5f\u897f 11 \u9009 5\",\"3\":\"Jiangxi 11\/5\",\"4\":\"Jiangxi 11\/5\",\"5\":\"Jiangxi 11\/5\"}",
        "game_code": "jx11xuan5_gf",
        "dlc_enabled": "0",
        "progressive": "0",
        "flash_enabled": "1",
        "offline_enabled": "0",
        "mobile_enabled": "0",
        "note": null,
        "status": "1",
        "flag_show_in_site": "1",
        "no_cash_back": "0",
        "void_bet": "0",
        "attributes": null,
        "game_order": null,
        "html_five_enabled": "1",
        "english_name": "Jiangxi 11\/5",
        "external_game_id": "jx11xuan5_gf",
        "clientid": null,
        "moduleid": null,
        "related_game_desc_id": null,
        "enabled_freespin": "0",
        "sub_game_provider": null,
        "enabled_on_android": "0",
        "enabled_on_ios": "0",
        "flag_new_game": "0",
        "demo_link": null,
        "game_type_code": "lottery"
    },
    {
        "game_platform_id": "307",
        "game_name": "_json:{\"1\":\"Shanghai 11\/5\",\"2\":\"\u4e0a\u6d77 11 \u9009 5\",\"3\":\"Shanghai 11\/5\",\"4\":\"Shanghai 11\/5\",\"5\":\"Shanghai 11\/5\"}",
        "game_code": "sh11xuan5_gf",
        "dlc_enabled": "0",
        "progressive": "0",
        "flash_enabled": "1",
        "offline_enabled": "0",
        "mobile_enabled": "0",
        "note": null,
        "status": "1",
        "flag_show_in_site": "1",
        "no_cash_back": "0",
        "void_bet": "0",
        "attributes": null,
        "game_order": null,
        "html_five_enabled": "1",
        "english_name": "Shanghai 11\/5",
        "external_game_id": "sh11xuan5_gf",
        "clientid": null,
        "moduleid": null,
        "related_game_desc_id": null,
        "enabled_freespin": "0",
        "sub_game_provider": null,
        "enabled_on_android": "0",
        "enabled_on_ios": "0",
        "flag_new_game": "0",
        "demo_link": null,
        "game_type_code": "lottery"
    },
    {
        "game_platform_id": "307",
        "game_name": "_json:{\"1\":\"Lotto 3D\",\"2\":\"\u798f\u5f69 3D\",\"3\":\"Lotto 3D\",\"4\":\"Lotto 3D\",\"5\":\"Lotto 3D\"}",
        "game_code": "fc3d_gf",
        "dlc_enabled": "0",
        "progressive": "0",
        "flash_enabled": "1",
        "offline_enabled": "0",
        "mobile_enabled": "0",
        "note": null,
        "status": "1",
        "flag_show_in_site": "1",
        "no_cash_back": "0",
        "void_bet": "0",
        "attributes": null,
        "game_order": null,
        "html_five_enabled": "1",
        "english_name": "Lotto 3D",
        "external_game_id": "fc3d_gf",
        "clientid": null,
        "moduleid": null,
        "related_game_desc_id": null,
        "enabled_freespin": "0",
        "sub_game_provider": null,
        "enabled_on_android": "0",
        "enabled_on_ios": "0",
        "flag_new_game": "0",
        "demo_link": null,
        "game_type_code": "lottery"
    },
    {
        "game_platform_id": "307",
        "game_name": "_json:{\"1\":\"Sports Lotto\",\"2\":\"\u6392\u5217 3\",\"3\":\"Sports Lotto\",\"4\":\"Sports Lotto\",\"5\":\"Sports Lotto\"}",
        "game_code": "pailie3_gf",
        "dlc_enabled": "0",
        "progressive": "0",
        "flash_enabled": "1",
        "offline_enabled": "0",
        "mobile_enabled": "0",
        "note": null,
        "status": "1",
        "flag_show_in_site": "1",
        "no_cash_back": "0",
        "void_bet": "0",
        "attributes": null,
        "game_order": null,
        "html_five_enabled": "1",
        "english_name": "Sports Lotto",
        "external_game_id": "pailie3_gf",
        "clientid": null,
        "moduleid": null,
        "related_game_desc_id": null,
        "enabled_freespin": "0",
        "sub_game_provider": null,
        "enabled_on_android": "0",
        "enabled_on_ios": "0",
        "flag_new_game": "0",
        "demo_link": null,
        "game_type_code": "lottery"
    }
]